cresnextws/__init__.py
cresnextws/client.py
cresnextws/data_event_manager.py
cresnextws-0.1.9.dist-info/licenses/LICENSE
cresnextws-0.1.9.dist-info/METADATA
cresnextws-0.1.9.dist-info/WHEEL
cresnextws-0.1.9.dist-info/top_level.txt
cresnextws-0.1.9.dist-info/RECORD
