Metadata-Version: 2.4
Name: cresnextws
Version: 0.1.9
Summary: Crestron CresNext WebSocket API Client
Author: Scott Shanafelt
Project-URL: Homepage, https://github.com/jetsoncontrols/cresnextws
Project-URL: Bug Reports, https://github.com/jetsoncontrols/cresnextws/issues
Project-URL: Source, https://github.com/jetsoncontrols/cresnextws
Keywords: crestron,cresnext,websocket,api,client
Classifier: Development Status :: 3 - Alpha
Classifier: Intended Audience :: Developers
Classifier: Operating System :: OS Independent
Classifier: Programming Language :: Python :: 3
Classifier: Programming Language :: Python :: 3.8
Classifier: Programming Language :: Python :: 3.9
Classifier: Programming Language :: Python :: 3.10
Classifier: Programming Language :: Python :: 3.11
Classifier: Programming Language :: Python :: 3.12
Classifier: Topic :: Software Development :: Libraries :: Python Modules
Classifier: Topic :: System :: Hardware :: Hardware Drivers
Requires-Python: >=3.8
License-File: LICENSE
Requires-Dist: websockets>=11.0
Requires-Dist: aiohttp>=3.8.0
Provides-Extra: dev
Requires-Dist: pytest>=7.0; extra == "dev"
Requires-Dist: pytest-asyncio>=0.20.0; extra == "dev"
Requires-Dist: black>=22.0; extra == "dev"
Requires-Dist: flake8>=5.0; extra == "dev"
Requires-Dist: mypy>=1.0; extra == "dev"
Dynamic: license-file
